code_instrumentation/__init__.py
code_instrumentation/add_logging_level.py
code_instrumentation/timer/__init__.py
code_instrumentation/timer/timer.py
commissioning_tools/__init__.py
commissioning_tools/fluid_dynamics_relationships.py
commissioning_tools/hotwire.py
commissioning_tools/lib.py
commissioning_tools/physical_constants.py
commissioning_tools/plotting.py
commissioning_tools/pressure.py
commissioning_tools/tunnel_conditions.py
commissioning_tools/units.py
aiolos_commissioning_tools-0.2.8.dist-info/LICENSE
aiolos_commissioning_tools-0.2.8.dist-info/METADATA
aiolos_commissioning_tools-0.2.8.dist-info/WHEEL
aiolos_commissioning_tools-0.2.8.dist-info/top_level.txt
aiolos_commissioning_tools-0.2.8.dist-info/RECORD
